configguard/__init__.py
configguard/config.py
configguard/exceptions.py
configguard/log.py
configguard/schema.py
configguard/section.py
configguard/setting.py
configguard/handlers/__init__.py
configguard/handlers/base.py
configguard/handlers/json_handler.py
configguard/handlers/sqlite_handler.py
configguard/handlers/toml_handler.py
configguard/handlers/yaml_handler.py
configguard-0.6.1.dist-info/licenses/LICENSE
configguard-0.6.1.dist-info/METADATA
configguard-0.6.1.dist-info/WHEEL
configguard-0.6.1.dist-info/top_level.txt
configguard-0.6.1.dist-info/RECORD
