Metadata-Version: 2.4
Name: configguard
Version: 0.6.1
Summary: A robust, schema-driven configuration management library for Python with encryption, versioning, nested sections, and multiple backends.
Author-email: ParisNeo <parisneoai@gmail.com>
License-Expression: Apache-2.0
Project-URL: Homepage, https://github.com/ParisNeo/ConfigGuard
Project-URL: Repository, https://github.com/ParisNeo/ConfigGuard.git
Project-URL: Documentation, https://parisneo.github.io/ConfigGuard/
Project-URL: Issues, https://github.com/ParisNeo/ConfigGuard/issues
Project-URL: Changelog, https://github.com/ParisNeo/ConfigGuard/blob/main/CHANGELOG.md
Keywords: config,configuration,settings,schema,validation,encryption,versioning,migration,json,yaml,toml,sqlite,ini,settings management,options,nested config,sections,dynamic config
Classifier: Development Status :: 4 - Beta
Classifier: Intended Audience :: Developers
Classifier: Programming Language :: Python :: 3
Classifier: Programming Language :: Python :: 3.8
Classifier: Programming Language :: Python :: 3.9
Classifier: Programming Language :: Python :: 3.10
Classifier: Programming Language :: Python :: 3.11
Classifier: Programming Language :: Python :: 3.12
Classifier: Operating System :: OS Independent
Classifier: Topic :: Software Development :: Libraries :: Python Modules
Classifier: Topic :: Utilities
Classifier: Typing :: Typed
Requires-Python: >=3.8
License-File: LICENSE
Requires-Dist: ascii_colors>=0.10.1
Requires-Dist: packaging>=20.0
Provides-Extra: encryption
Requires-Dist: cryptography>=3.4; extra == "encryption"
Provides-Extra: yaml
Requires-Dist: pyyaml>=6.0; extra == "yaml"
Provides-Extra: toml
Requires-Dist: toml>=0.10.2; extra == "toml"
Provides-Extra: all
Requires-Dist: configguard[encryption,toml,yaml]; extra == "all"
Provides-Extra: dev
Requires-Dist: pytest>=7.0; extra == "dev"
Requires-Dist: pytest-cov>=3.0; extra == "dev"
Requires-Dist: black>=23.0; extra == "dev"
Requires-Dist: ruff>=0.1.0; extra == "dev"
Requires-Dist: mypy>=1.0; extra == "dev"
Requires-Dist: cryptography>=3.4; extra == "dev"
Requires-Dist: pyyaml>=6.0; extra == "dev"
Requires-Dist: toml>=0.10.2; extra == "dev"
Requires-Dist: sphinx>=6.0; extra == "dev"
Requires-Dist: sphinx-rtd-theme>=1.0; extra == "dev"
Requires-Dist: PyQt5>=5.15; extra == "dev"
Dynamic: license-file
